new-RTL-trials/larger_heap.v
module heap(
    input clk,
    input rst_n,
    input push,
    input pop,
    input [7:0] data_in,
    output reg [7:0] data_out,
    output reg empty,
    output reg full
);

    reg [7:0] heap_array [0:15]; // Array of 16 vector registers, each 8 bits wide
    reg [4:0] heap_size;
    reg [4:0] i;

    reg [4:0] state;
    reg [4:0] idx;
    reg [4:0] parent_idx;
    reg [4:0] left_idx;
    reg [4:0] right_idx;
    reg [4:0] largest_idx;

    reg [7:0] temp;

    localparam IDLE = 5'd0,
               PUSH = 5'd1,
               POP = 5'd2,
               HEAPIFY_UP = 5'd3,
               HEAPIFY_DOWN = 5'd4;

    always @(posedge clk or negedge rst_n) begin
        if (!rst_n) begin
            heap_size <= 5'd0;
            empty <= 1'b1;
            full <= 1'b0;
            state <= IDLE;
            for (i = 0; i < 16; i = i + 1) begin
                heap_array[i] <= 8'd0; // Initialize all elements to zero
            end
        end else begin
            case (state)
                IDLE: begin
                    if (push && !full) begin
                        $display("Pushing value %d", data_in);
                        heap_size <= heap_size + 1;
                        heap_array[heap_size] <= data_in; // Add new element at the end
                        empty <= 1'b0;
                        if (heap_size == 5'd15)
                            full <= 1'b1;
                        else
                            full <= 1'b0;
                        state <= HEAPIFY_UP;
                        idx <= heap_size; // Start heapify-up from the newly added element
                    end else if (pop && !empty) begin
                        $display("Popping value %d", heap_array[0]);
                        data_out <= heap_array[0]; // Output the root element
                        heap_array[0] <= heap_array[heap_size-1]; // Move the last element to the root
                        heap_size <= heap_size - 1;
                        full <= 1'b0;
                        if (heap_size == 5'd0)
                            empty <= 1'b1;
                        else
                            empty <= 1'b0;
                        state <= HEAPIFY_DOWN;
                        idx <= 0; // Start heapify-down from the root
                    end
                end

                HEAPIFY_UP: begin
                    parent_idx = (idx - 1) >> 1;
                    if (idx > 0 && heap_array[idx] > heap_array[parent_idx]) begin
                        $display("Heapify up: swapping %d and %d", heap_array[idx], heap_array[parent_idx]);
                        temp = heap_array[idx];
                        heap_array[idx] = heap_array[parent_idx];
                        heap_array[parent_idx] = temp;
                        idx = parent_idx; // Move up to the parent index
                    end else begin
                        state <= IDLE;
                    end
                end

                HEAPIFY_DOWN: begin
                    left_idx = 2*idx + 1;
                    right_idx = 2*idx + 2;
                    largest_idx = idx;

                    if (left_idx < heap_size && heap_array[left_idx] > heap_array[largest_idx])
                        largest_idx = left_idx;
                    if (right_idx < heap_size && heap_array[right_idx] > heap_array[largest_idx])
                        largest_idx = right_idx;

                    if (largest_idx != idx) begin
                        $display("Heapify down: swapping %d and %d", heap_array[idx], heap_array[largest_idx]);
                        temp = heap_array[idx];
                        heap_array[idx] = heap_array[largest_idx];
                        heap_array[largest_idx] = temp;
                        idx = largest_idx; // Move down to the largest child index
                    end else begin
                        state <= IDLE;
                    end
                end

            endcase
        end
    end

endmodule

new-RTL-trials/larger_heap_tb.v
`timescale 1ns / 1ps

module heap_tb;

    // Inputs
    reg clk;
    reg rst_n;
    reg push;
    reg pop;
    reg [7:0] data_in;

    // Outputs
    wire [7:0] data_out;
    wire empty;
    wire full;

    // Instantiate the Unit Under Test (UUT)
    heap uut (
        .clk(clk), 
        .rst_n(rst_n), 
        .push(push), 
        .pop(pop), 
        .data_in(data_in), 
        .data_out(data_out), 
        .empty(empty), 
        .full(full)
    );

    // Clock generation
    always #5 clk = ~clk;

    initial begin
        // Initialize Inputs
        clk = 0;
        rst_n = 0;
        push = 0;
        pop = 0;
        data_in = 0;

        // Dump waves
        $dumpfile("heap_tb.vcd");
        $dumpvars(0, heap_tb);

        // Display initialization message
        $display("Starting simulation");

        // Reset the heap
        #10;
        rst_n = 1;
        $display("Applying reset");

        // Push random elements into the heap
        for (i = 0; i < 16; i = i + 1) begin
            push_element($random % 256);
        end

        // Pop elements from the heap
        for (i = 0; i < 16; i = i + 1) begin
            pop_element();
        end

        // End simulation
        #10;
        $finish;
    end

    integer i;

    task push_element(input [7:0] value);
        begin
            @(negedge clk);
            $display("Pushing element %d", value);
            data_in = value;
            push = 1;
            @(negedge clk);
            push = 0;
            data_in = 0;
            wait_for_idle();
        end
    endtask

    task pop_element;
        begin
            @(negedge clk);
            $display("Popping element");
            pop = 1;
            @(negedge clk);
            pop = 0;
            wait_for_idle();
        end
    endtask

    task wait_for_idle;
        begin
            while (uut.state != uut.IDLE) begin
                @(negedge clk);
            end
            $display("Heap is idle");
        end
    endtask

endmodule

new-RTL-trials/heap_tb.vcd
$date
	Mon Jul 22 19:27:27 2024
$end
$version
	Icarus Verilog
$end
$timescale
	1ps
$end
$scope module heap_tb $end
$var wire 1 ! full $end
$var wire 1 " empty $end
$var wire 8 # data_out [7:0] $end
$var reg 1 $ clk $end
$var reg 8 % data_in [7:0] $end
$var reg 1 & pop $end
$var reg 1 ' push $end
$var reg 1 ( rst_n $end
$var integer 32 ) i [31:0] $end
$scope module uut $end
$var wire 1 $ clk $end
$var wire 8 * data_in [7:0] $end
$var wire 1 & pop $end
$var wire 1 ' push $end
$var wire 1 ( rst_n $end
$var parameter 5 + HEAPIFY_DOWN $end
$var parameter 5 , HEAPIFY_UP $end
$var parameter 5 - IDLE $end
$var parameter 5 . POP $end
$var parameter 5 / PUSH $end
$var reg 8 0 data_out [7:0] $end
$var reg 1 " empty $end
$var reg 1 ! full $end
$var reg 5 1 heap_size [4:0] $end
$var reg 5 2 i [4:0] $end
$var reg 5 3 idx [4:0] $end
$var reg 5 4 largest_idx [4:0] $end
$var reg 5 5 left_idx [4:0] $end
$var reg 5 6 parent_idx [4:0] $end
$var reg 5 7 right_idx [4:0] $end
$var reg 5 8 state [4:0] $end
$var reg 8 9 temp [7:0] $end
$upscope $end
$scope task pop_element $end
$upscope $end
$scope task push_element $end
$var reg 8 : value [7:0] $end
$upscope $end
$scope task wait_for_idle $end
$upscope $end
$upscope $end
$enddefinitions $end
$comment Show the parameter values. $end
$dumpall
b1 /
b10 .
b0 -
b11 ,
b100 +
$end
#0
$dumpvars
bx :
bx 9
b0 8
bx 7
bx 6
bx 5
bx 4
bx 3
b10000 2
b0 1
bx 0
b0 *
bx )
0(
0'
0&
b0 %
0$
bx #
1"
0!
$end
#5000
b10000 2
1$
#10000
1'
b100100 %
b100100 *
0$
b100100 :
b0 )
1(
#15000
b0 3
b11 8
0"
b1 1
1$
#20000
b0 %
b0 *
0'
0$
#25000
b0 8
b11111 6
1$
#30000
b10000001 :
b1 )
0$
#35000
1$
#40000
1'
b10000001 %
b10000001 *
0$
#45000
b1 3
b11 8
b10 1
1$
#50000
b0 %
b0 *
0'
0$
#55000
b0 3
b10000001 9
b0 6
1$
#60000
0$
#65000
b0 8
b11111 6
1$
#70000
b1001 :
b10 )
0$
#75000
1$
#80000
1'
b1001 %
b1001 *
0$
#85000
b10 3
b11 8
b11 1
1$
#90000
b0 %
b0 *
0'
0$
#95000
b0 8
b0 6
1$
#100000
b1100011 :
b11 )
0$
#105000
1$
#110000
1'
b1100011 %
b1100011 *
0$
#115000
b11 3
b11 8
b100 1
1$
#120000
b0 %
b0 *
0'
0$
#125000
b1 3
b1100011 9
b1 6
1$
#130000
0$
#135000
b0 8
b0 6
1$
#140000
b1101 :
b100 )
0$
#145000
1$
#150000
1'
b1101 %
b1101 *
0$
#155000
b100 3
b11 8
b101 1
1$
#160000
b0 %
b0 *
0'
0$
#165000
b0 8
b1 6
1$
#170000
b10001101 :
b101 )
0$
#175000
1$
#180000
1'
b10001101 %
b10001101 *
0$
#185000
b101 3
b11 8
b110 1
1$
#190000
b0 %
b0 *
0'
0$
#195000
b10 3
b10001101 9
b10 6
1$
#200000
0$
#205000
b0 3
b0 6
1$
#210000
0$
#215000
b0 8
b11111 6
1$
#220000
b1100101 :
b110 )
0$
#225000
1$
#230000
1'
b1100101 %
b1100101 *
0$
#235000
b110 3
b11 8
b111 1
1$
#240000
b0 %
b0 *
0'
0$
#245000
b0 8
b10 6
1$
#250000
b10010 :
b111 )
0$
#255000
1$
#260000
1'
b10010 %
b10010 *
0$
#265000
b111 3
b11 8
b1000 1
1$
#270000
b0 %
b0 *
0'
0$
#275000
b0 8
b11 6
1$
#280000
b1 :
b1000 )
0$
#285000
1$
#290000
1'
b1 %
b1 *
0$
#295000
b1000 3
b11 8
b1001 1
1$
#300000
b0 %
b0 *
0'
0$
#305000
b0 8
1$
#310000
b1101 :
b1001 )
0$
#315000
1$
#320000
1'
b1101 %
b1101 *
0$
#325000
b1001 3
b11 8
b1010 1
1$
#330000
b0 %
b0 *
0'
0$
#335000
b0 8
b100 6
1$
#340000
b1110110 :
b1010 )
0$
#345000
1$
#350000
1'
b1110110 %
b1110110 *
0$
#355000
b1010 3
b11 8
b1011 1
1$
#360000
b0 %
b0 *
0'
0$
#365000
b100 3
b1110110 9
1$
#370000
0$
#375000
b1 3
b1 6
1$
#380000
0$
#385000
b0 8
b0 6
1$
#390000
b111101 :
b1011 )
0$
#395000
1$
#400000
1'
b111101 %
b111101 *
0$
#405000
b1011 3
b11 8
b1100 1
1$
#410000
b0 %
b0 *
0'
0$
#415000
b101 3
b111101 9
b101 6
1$
#420000
0$
#425000
b0 8
b10 6
1$
#430000
b11101101 :
b1100 )
0$
#435000
1$
#440000
1'
b11101101 %
b11101101 *
0$
#445000
b1100 3
b11 8
b1101 1
1$
#450000
b0 %
b0 *
0'
0$
#455000
b101 3
b11101101 9
b101 6
1$
#460000
0$
#465000
b10 3
b10 6
1$
#470000
0$
#475000
b0 3
b0 6
1$
#480000
0$
#485000
b0 8
b11111 6
1$
#490000
b10001100 :
b1101 )
0$
#495000
1$
#500000
1'
b10001100 %
b10001100 *
0$
#505000
b1101 3
b11 8
b1110 1
1$
#510000
b0 %
b0 *
0'
0$
#515000
b110 3
b10001100 9
b110 6
1$
#520000
0$
#525000
b0 8
b10 6
1$
#530000
b11111001 :
b1110 )
0$
#535000
1$
#540000
1'
b11111001 %
b11111001 *
0$
#545000
b1110 3
b11 8
b1111 1
1$
#550000
b0 %
b0 *
0'
0$
#555000
b110 3
b11111001 9
b110 6
1$
#560000
0$
#565000
b10 3
b10 6
1$
#570000
0$
#575000
b0 3
b0 6
1$
#580000
0$
#585000
b0 8
b11111 6
1$
#590000
b11000110 :
b1111 )
0$
#595000
1$
#600000
1'
b11000110 %
b11000110 *
0$
#605000
b1111 3
b11 8
1!
b10000 1
1$
#610000
b0 %
b0 *
0'
0$
#615000
b111 3
b11000110 9
b111 6
1$
#620000
0$
#625000
b11 3
b11 6
1$
#630000
0$
#635000
b1 3
b1 6
1$
#640000
0$
#645000
b0 8
b0 6
1$
#650000
b0 )
0$
#655000
1$
#660000
1&
0$
#665000
b0 3
b100 8
0!
b1111 1
b11111001 #
b11111001 0
1$
#670000
0&
0$
#675000
b10 3
b10010 9
b10 4
b10 7
b1 5
1$
#680000
0$
#685000
b110 3
b110 4
b110 7
b101 5
1$
#690000
0$
#695000
b1110 3
b1110 4
b1110 7
b1101 5
1$
#700000
0$
#705000
b0 8
b11110 7
b11101 5
1$
#710000
b1 )
0$
#715000
1$
#720000
1&
0$
#725000
b0 3
b100 8
b1110 1
b11101101 #
b11101101 0
1$
#730000
0&
0$
#735000
b1 3
b1 4
b10 7
b1 5
1$
#740000
0$
#745000
b11 3
b11 4
b100 7
b11 5
1$
#750000
0$
#755000
b111 3
b111 4
b1000 7
b111 5
1$
#760000
0$
#765000
b0 8
b10000 7
b1111 5
1$
#770000
b10 )
0$
#775000
1$
#780000
1&
0$
#785000
b0 3
b100 8
b1101 1
b11000110 #
b11000110 0
1$
#790000
0&
0$
#795000
b10 3
b1100101 9
b10 4
b10 7
b1 5
1$
#800000
0$
#805000
b110 3
b110 4
b110 7
b101 5
1$
#810000
0$
#815000
b0 8
b1110 7
b1101 5
1$
#820000
b11 )
0$
#825000
1$
#830000
1&
0$
#835000
b0 3
b100 8
b1100 1
b10001101 #
b10001101 0
1$
#840000
0&
0$
#845000
b10 3
b111101 9
b10 4
b10 7
b1 5
1$
#850000
0$
#855000
b101 3
b101 4
b110 7
b101 5
1$
#860000
0$
#865000
b0 8
b1100 7
b1011 5
1$
#870000
b100 )
0$
#875000
1$
#880000
1&
0$
#885000
b0 3
b100 8
b1011 1
b10001100 #
b10001100 0
1$
#890000
0&
0$
#895000
b10 3
b1001 9
b10 4
b10 7
b1 5
1$
#900000
0$
#905000
b110 3
b110 4
b110 7
b101 5
1$
#910000
0$
#915000
b0 8
b1110 7
b1101 5
1$
#920000
b101 )
0$
#925000
1$
#930000
1&
0$
#935000
b0 3
b100 8
b1010 1
b10000001 #
b10000001 0
1$
#940000
0&
0$
#945000
b1 3
b1101 9
b1 4
b10 7
b1 5
1$
#950000
0$
#955000
b100 3
b100 4
b100 7
b11 5
1$
#960000
0$
#965000
b0 8
b1010 7
b1001 5
1$
#970000
b110 )
0$
#975000
1$
#980000
1&
0$
#985000
b0 3
b100 8
b1001 1
b1110110 #
b1110110 0
1$
#990000
0&
0$
#995000
b10 3
b10 4
b10 7
b1 5
1$
#1000000
0$
#1005000
b101 3
b101 4
b110 7
b101 5
1$
#1010000
0$
#1015000
b0 8
b1100 7
b1011 5
1$
#1020000
b111 )
0$
#1025000
1$
#1030000
1&
0$
#1035000
b0 3
b100 8
b1000 1
b1100101 #
b1100101 0
1$
#1040000
0&
0$
#1045000
b1 3
b1 9
b1 4
b10 7
b1 5
1$
#1050000
0$
#1055000
b11 3
b11 4
b100 7
b11 5
1$
#1060000
0$
#1065000
b111 3
b111 4
b1000 7
b111 5
1$
#1070000
0$
#1075000
b0 8
b10000 7
b1111 5
1$
#1080000
b1000 )
0$
#1085000
1$
#1090000
1&
0$
#1095000
b0 3
b100 8
b111 1
b1100011 #
b1100011 0
1$
#1100000
0&
0$
#1105000
b10 3
b10 4
b10 7
b1 5
1$
#1110000
0$
#1115000
b101 3
b101 4
b110 7
b101 5
1$
#1120000
0$
#1125000
b0 8
b1100 7
b1011 5
1$
#1130000
b1001 )
0$
#1135000
1$
#1140000
1&
0$
#1145000
b0 3
b100 8
b110 1
b111101 #
b111101 0
1$
#1150000
0&
0$
#1155000
b1 3
b1001 9
b1 4
b10 7
b1 5
1$
#1160000
0$
#1165000
b11 3
b11 4
b100 7
b11 5
1$
#1170000
0$
#1175000
b0 8
b1000 7
b111 5
1$
#1180000
b1010 )
0$
#1185000
1$
#1190000
1&
0$
#1195000
b0 3
b100 8
b101 1
b100100 #
b100100 0
1$
#1200000
0&
0$
#1205000
b1 3
b1 9
b1 4
b10 7
b1 5
1$
#1210000
0$
#1215000
b100 3
b100 4
b100 7
b11 5
1$
#1220000
0$
#1225000
b0 8
b1010 7
b1001 5
1$
#1230000
b1011 )
0$
#1235000
1$
#1240000
1&
0$
#1245000
b0 3
b100 8
b100 1
b10010 #
b10010 0
1$
#1250000
0&
0$
#1255000
b1 3
b1 4
b10 7
b1 5
1$
#1260000
0$
#1265000
b11 3
b11 4
b100 7
b11 5
1$
#1270000
0$
#1275000
b0 8
b1000 7
b111 5
1$
#1280000
b1100 )
0$
#1285000
1$
#1290000
1&
0$
#1295000
b0 3
b100 8
b11 1
b1101 #
b1101 0
1$
#1300000
0&
0$
#1305000
b10 3
b10 4
b10 7
b1 5
1$
#1310000
0$
#1315000
b0 8
b110 7
b101 5
1$
#1320000
b1101 )
0$
#1325000
1$
#1330000
1&
0$
#1335000
b0 3
b100 8
b10 1
1$
#1340000
0&
0$
#1345000
b1 3
b1 4
b10 7
b1 5
1$
#1350000
0$
#1355000
b0 8
b100 7
b11 5
1$
#1360000
b1110 )
0$
#1365000
1$
#1370000
1&
0$
#1375000
b0 3
b100 8
b1 1
b1001 #
b1001 0
1$
#1380000
0&
0$
#1385000
b0 8
b0 4
b10 7
b1 5
1$
#1390000
b1111 )
0$
#1395000
1$
#1400000
1&
0$
#1405000
b100 8
b0 1
b1 #
b1 0
1$
#1410000
0&
0$
#1415000
b0 8
1$
#1420000
b10000 )
0$
